setup.py
drainhunter/__init__.py
drainhunter/core.py
drainhunter/server.py
drainhunter/web.py
drainhunter/wsgi.py
drainhunter.egg-info/PKG-INFO
drainhunter.egg-info/SOURCES.txt
drainhunter.egg-info/dependency_links.txt
drainhunter.egg-info/not-zip-safe
drainhunter.egg-info/requires.txt
drainhunter.egg-info/top_level.txt
drainhunter/django/__init__.py
drainhunter/django/urls.py
drainhunter/django/views.py