Metadata-Version: 1.0
Name: drainhunter
Version: 0.2
Summary: Memory leaks investigation tool
Home-page: http://github.com/baverman/drainhunter
Author: Anton Bobrov
Author-email: bobrov@vl.ru
License: UNKNOWN
Platform: UNKNOWN
Classifier: Programming Language :: Python
Classifier: Intended Audience :: Developers
Classifier: License :: OSI Approved :: MIT License
Classifier: Development Status :: 4 - Beta
Classifier: Natural Language :: English
Classifier: Topic :: Software Development :: Debuggers
